pybuildtool/README.rst
pybuildtool/__init__.py
pybuildtool/wscript.example
pybuildtool/addons/__init__.py
pybuildtool/addons/watch/__init__.py
pybuildtool/addons/watch/application.py
pybuildtool/addons/watch/file_observer.py
pybuildtool/addons/watch/files/__init__.py
pybuildtool/addons/watch/files/browser_reload_notifier.py
pybuildtool/core/__init__.py
pybuildtool/core/context.py
pybuildtool/core/group.py
pybuildtool/core/rule.py
pybuildtool/core/task.py
pybuildtool/misc/__init__.py
pybuildtool/misc/collections_utils.py
pybuildtool/misc/path.py
pybuildtool/misc/python.py
pybuildtool/misc/resource.py
pybuildtool/misc/yaml_utils.py
pybuildtool/tests/__init__.py
pybuildtool/tools/__init__.py
pybuildtool/tools/ansibleplay.py
pybuildtool/tools/browserify.py
pybuildtool/tools/clean-css.py
pybuildtool/tools/concat.py
pybuildtool/tools/copy.py
pybuildtool/tools/cp.py
pybuildtool/tools/cppcheck.py
pybuildtool/tools/dot.py
pybuildtool/tools/doxygen.py
pybuildtool/tools/flatbuffers.py
pybuildtool/tools/gzip.py
pybuildtool/tools/handlebars.py
pybuildtool/tools/html-linter.py
pybuildtool/tools/jinja.py
pybuildtool/tools/jscs.py
pybuildtool/tools/jshint.py
pybuildtool/tools/less.py
pybuildtool/tools/lftp.py
pybuildtool/tools/metadata2fontface.py
pybuildtool/tools/msbuild.py
pybuildtool/tools/mustache.py
pybuildtool/tools/node-sass.py
pybuildtool/tools/nuget_restore.py
pybuildtool/tools/nunjucks.py
pybuildtool/tools/patch.py
pybuildtool/tools/pngcrush.py
pybuildtool/tools/postcss.py
pybuildtool/tools/protoc.py
pybuildtool/tools/pylint.py
pybuildtool/tools/requirejs.py
pybuildtool/tools/restructuredtext-lint.py
pybuildtool/tools/rjs.py
pybuildtool/tools/roscpplint.py
pybuildtool/tools/rsync.py
pybuildtool/tools/runit_sv.py
pybuildtool/tools/scp.py
pybuildtool/tools/shell.py
pybuildtool/tools/sphinx-apidoc.py
pybuildtool/tools/sphinx-build.py
pybuildtool/tools/splint.py
pybuildtool/tools/stylelint.py
pybuildtool/tools/stylus.py
pybuildtool/tools/ttf2eot.py
pybuildtool-2.0.44.dist-info/LICENSE
pybuildtool-2.0.44.dist-info/METADATA
pybuildtool-2.0.44.dist-info/WHEEL
pybuildtool-2.0.44.dist-info/top_level.txt
pybuildtool-2.0.44.dist-info/RECORD
