Metadata-Version: 2.1
Name: pybuildtool
Version: 2.0.44
Summary: Build utility to manage web resources.
Home-page: https://codeberg.org/dozymoe/PyBuildTool
Author: Fahri Reza
Author-email: i@dozy.moe
License: MIT
Project-URL: Bug Tracker, https://codeberg.org/dozymoe/PyBuildTool/issues
Classifier: Intended Audience :: Developers
Classifier: License :: OSI Approved :: MIT License
Classifier: Operating System :: OS Independent
Classifier: Programming Language :: Python
Classifier: Programming Language :: Python :: 3
License-File: LICENSE
Requires-Dist: locket
Requires-Dist: pyyaml
Requires-Dist: stringcase
Requires-Dist: watchdog
